{
  "type": "FeatureCollection",
  "features": [
    {
      "type": "Feature",
      "properties": {},
      "geometry": {
        "type": "Polygon",
        "coordinates": [
          [
            [
              23.70849609375,
              9.687398430760624
            ],
            [
              24.1259765625,
              9.709057068618222
            ],
            [
              24.2578125,
              9.817329187067783
            ],
            [
              24.63134765625,
              9.838979375579344
            ],
            [
              24.873046874999996,
              9.838979375579344
            ],
            [
              25.0927734375,
              10.293301000109114
            ],
            [
              25.751953125,
              10.531020008464989
            ],
            [
              25.9716796875,
              10.401377554543553
            ],
            [
              26.015625,
              10.14193168613103
            ],
            [
              26.34521484375,
              9.795677582829743
            ],
            [
              26.34521484375,
              9.579084335882534
            ],
            [
              26.60888671875,
              9.557417356841308
            ],
            [
              26.9384765625,
              9.579084335882534
            ],
            [
              27.88330078125,
              9.665738395188692
            ],
            [
              28.14697265625,
              9.340672181980947
            ],
            [
              28.762207031249996,
              9.362352822055605
            ],
            [
              29.091796875,
              9.838979375579344
            ],
            [
              29.53125,
              9.752370139173285
            ],
            [
              29.553222656249996,
              10.120301632173907
            ],
            [
              29.99267578125,
              10.401377554543553
            ],
            [
              30.827636718749996,
              9.752370139173285
            ],
            [
              31.26708984375,
              9.774024565864734
            ],
            [
              31.970214843749996,
              10.703791711680736
            ],
            [
              32.49755859375,
              11.049038346537106
            ],
            [
              32.36572265625,
              11.759814674441921
            ],
            [
              32.08007812499999,
              11.974844752931832
            ],
            [
              32.76123046875,
              11.953349393643416
            ],
            [
              32.76123046875,
              12.21118019150401
            ],
            [
              33.37646484375,
              12.254127737657381
            ],
            [
              33.06884765625,
              11.523087506868514
            ],
            [
              33.2666015625,
              10.682200600084114
            ],
            [
              34.013671875,
              10.14193168613103
            ],
            [
              33.85986328125,
              9.60074993224686
            ],
            [
              34.1015625,
              9.535748998133627
            ],
            [
              34.1015625,
              8.602747284770018
            ],
            [
              33.7939453125,
              8.428904092875392
            ],
            [
              33.59619140624999,
              8.450638800331001
            ],
            [
              33.22265625,
              8.428904092875392
            ],
            [
              33.22265625,
              8.254982704877875
            ],
            [
              33.02490234375,
              8.03747339584114
            ],
            [
              33.0029296875,
              7.885147283424331
            ],
            [
              33.42041015625,
              7.732765062729807
            ],
            [
              33.72802734375,
              7.645664723491027
            ],
            [
              34.07958984374999,
              7.18810087117902
            ],
            [
              34.541015625,
              6.730075707109153
            ],
            [
              35.04638671874999,
              6.489983332670651
            ],
            [
              34.9365234375,
              6.031310707125822
            ],
            [
              35.3759765625,
              5.266007882805511
            ],
            [
              35.5517578125,
              5.441022303717974
            ],
            [
              35.83740234375,
              5.331644153439766
            ],
            [
              35.8154296875,
              4.981505049328246
            ],
            [
              35.8154296875,
              4.762572524280281
            ],
            [
              34.43115234375,
              4.609278084409835
            ],
            [
              33.5302734375,
              3.732708321335859
            ],
            [
              33.02490234375,
              3.8423316311549156
            ],
            [
              32.34375,
              3.6888551431470478
            ],
            [
              32.14599609375,
              3.5572827265412794
            ],
            [
              31.70654296875,
              3.8204080831949407
            ],
            [
              31.552734374999996,
              3.6449998008920375
            ],
            [
              31.13525390625,
              3.8204080831949407
            ],
            [
              30.91552734375,
              3.46955730306146
            ],
            [
              29.729003906249996,
              4.434044005032582
            ],
            [
              29.7509765625,
              4.653079918274051
            ],
            [
              29.553222656249996,
              4.696879026871413
            ],
            [
              29.20166015625,
              4.36832042087623
            ],
            [
              28.762207031249996,
              4.499761743620538
            ],
            [
              28.4326171875,
              4.302591077119676
            ],
            [
              27.9931640625,
              4.499761743620538
            ],
            [
              27.443847656249996,
              5.134714634014455
            ],
            [
              27.24609375,
              5.61598581915534
            ],
            [
              26.47705078125,
              6.0968598188879355
            ],
            [
              26.34521484375,
              6.424483546180726
            ],
            [
              26.30126953125,
              6.664607562172585
            ],
            [
              25.7958984375,
              7.144498849647335
            ],
            [
              25.13671875,
              7.558546606093156
            ],
            [
              25.2685546875,
              7.798078531355303
            ],
            [
              24.93896484375,
              7.928674801364048
            ],
            [
              24.8291015625,
              8.124491290861204
            ],
            [
              24.45556640625,
              8.233237111274553
            ],
            [
              23.994140624999996,
              8.407168163601076
            ],
            [
              24.169921875,
              8.667918002363134
            ],
            [
              23.4228515625,
              8.776510716052352
            ],
            [
              23.37890625,
              9.145486056167277
            ],
            [
              23.5986328125,
              9.253936156814463
            ],
            [
              23.70849609375,
              9.687398430760624
            ]
          ]
        ]
      }
    }
  ]
}
